odoo/addons/sale_report_supplier_filter/README.rst
odoo/addons/sale_report_supplier_filter/__init__.py
odoo/addons/sale_report_supplier_filter/__manifest__.py
odoo/addons/sale_report_supplier_filter/i18n/es.po
odoo/addons/sale_report_supplier_filter/i18n/sale_report_supplier_filter.pot
odoo/addons/sale_report_supplier_filter/readme/CONTRIBUTORS.rst
odoo/addons/sale_report_supplier_filter/readme/DESCRIPTION.rst
odoo/addons/sale_report_supplier_filter/readme/USAGE.rst
odoo/addons/sale_report_supplier_filter/reports/__init__.py
odoo/addons/sale_report_supplier_filter/reports/report_all_channels_sales.py
odoo/addons/sale_report_supplier_filter/reports/sale_report.py
odoo/addons/sale_report_supplier_filter/reports/sale_report_views.xml
odoo/addons/sale_report_supplier_filter/static/description/icon.png
odoo/addons/sale_report_supplier_filter/static/description/index.html
odoo11_addon_sale_report_supplier_filter-11.0.1.0.0.99.dev5.dist-info/METADATA
odoo11_addon_sale_report_supplier_filter-11.0.1.0.0.99.dev5.dist-info/WHEEL
odoo11_addon_sale_report_supplier_filter-11.0.1.0.0.99.dev5.dist-info/top_level.txt
odoo11_addon_sale_report_supplier_filter-11.0.1.0.0.99.dev5.dist-info/RECORD
